hook/__init__.py
hook/core.py
TorrentsUsefulStuff_TorrentofShame-1.0.4.dist-info/LICENSE
TorrentsUsefulStuff_TorrentofShame-1.0.4.dist-info/METADATA
TorrentsUsefulStuff_TorrentofShame-1.0.4.dist-info/WHEEL
TorrentsUsefulStuff_TorrentofShame-1.0.4.dist-info/top_level.txt
TorrentsUsefulStuff_TorrentofShame-1.0.4.dist-info/RECORD
