Metadata-Version: 2.1
Name: TorrentsUsefulStuff-TorrentofShame
Version: 1.0.4
Summary: A python implementation of the Hooks found in Garry's Mod; however, usage of this has nothing to do with Garry's Mod itself.
Home-page: https://gitlab.com/torrentofshame/python-someusefulreusablestuff
Author: TorrentofShame
Author-email: t@torrentofshame.com
License: UNKNOWN
Platform: UNKNOWN
Classifier: Programming Language :: Python :: 3
Classifier: License :: OSI Approved :: MIT License
Classifier: Operating System :: OS Independent
Requires-Python: >=3.8
